streamlit_project_template/__init__.py
streamlit_project_template/createtemplate.py
streamlit_project_template/main.py
streamlit_project_template/template/__init__.py
streamlit_project_template/template/app.py
streamlit_project_template/template/src/__init__.py
streamlit_project_template/template/src/callbacks.py
streamlit_project_template/template/src/components.py
streamlit_project_template/template/src/pages.py
streamlit_project_template-0.1.2.dist-info/LICENSE
streamlit_project_template-0.1.2.dist-info/METADATA
streamlit_project_template-0.1.2.dist-info/WHEEL
streamlit_project_template-0.1.2.dist-info/entry_points.txt
streamlit_project_template-0.1.2.dist-info/top_level.txt
streamlit_project_template-0.1.2.dist-info/RECORD
