Metadata-Version: 2.1
Name: streamlit-project-template
Version: 0.1.2
Summary: A solid project structure from basit to advanced streamlit applications.
Author: Mehmet Can Demir
Author-email: mhmtcndmr01@gmail.com
Project-URL: Documentation, https://github.com/mcandemir/streamlit-project-template/blob/master/README.md
Project-URL: Repository, https://github.com/mcandemir/streamlit-project-template
Classifier: Intended Audience :: Developers
Classifier: Programming Language :: Python :: 3.6
Classifier: Environment :: Console
Classifier: Development Status :: 3 - Alpha
Classifier: Programming Language :: Python :: 3.12
Requires-Python: >=3.6
License-File: LICENSE
Requires-Dist: streamlit
Provides-Extra: extras
Requires-Dist: streamlit-extras ; extra == 'extras'
